geoedfframework/GeoEDFExecutor.py
geoedfframework/GeoEDFPlugin.py
geoedfframework/__init__.py
geoedfframework/utils/GeoEDFError.py
geoedfframework/utils/GeoEDFHTMLParser.py
geoedfframework/utils/__init__.py
geoedfframework-0.7.0.data/scripts/collect.py
geoedfframework-0.7.0.data/scripts/gen-keypair.py
geoedfframework-0.7.0.data/scripts/merge.py
geoedfframework-0.7.0.data/scripts/run-connector-plugin.py
geoedfframework-0.7.0.data/scripts/run-processor-plugin.py
geoedfframework-0.7.0.data/scripts/run-workflow-stage.sh
geoedfframework-0.7.0.dist-info/LICENSE
geoedfframework-0.7.0.dist-info/METADATA
geoedfframework-0.7.0.dist-info/WHEEL
geoedfframework-0.7.0.dist-info/top_level.txt
geoedfframework-0.7.0.dist-info/RECORD
