Metadata-Version: 2.1
Name: geoedfframework
Version: 0.7.0
Summary: GeoEDF Connector Processor Framework
Home-page: https://geoedf.readthedocs.io
Author: Rajesh Kalyanam
Author-email: rkalyanapurdue@gmail.com
License: MIT
Platform: UNKNOWN
Requires-Python: ~=3.6
License-File: LICENSE
Requires-Dist: pyyaml
Requires-Dist: regex
Requires-Dist: cffi
Requires-Dist: cryptography
